Workbook

Sheet 📊 Resumen
B2: 💰 REPORTE MENSUAL DE FINANZAS PERSONALES
B4: INGRESOS | D4: EGRESOS | F4: BALANCE
B6: =Transacciones!C2 -> 2853000 | D6: =Transacciones!C3 -> 1528000 | F6: =Transacciones!C4 -> 1325000
B8: GASTOS POR CATEGORÍA
B9: Categoría | C9: Total Gastado | D9: % del Total | E9: vs. Presupuesto | F9: Estado
B10: ● Vivienda | C10: =SUMIF(Transacciones!E:E,"Vivienda",Transacciones!D:D) -> 700000 | D10: =IF(Transacciones!C3>0,C10/Transacciones!C3,0) -> 0.45811518 | E10: =C10-IFERROR(VLOOKUP("Vivienda",Presupuesto!A:B,2,0),0) -> -500000 | F10: =IF(E10<=0,"✅ OK","⚠️ Excedido") -> ✅ OK
B11: ● Deudas | C11: =SUMIF(Transacciones!E:E,"Deudas",Transacciones!D:D) -> 70000 | D11: =IF(Transacciones!C3>0,C11/Transacciones!C3,0) -> 0.045811518 | E11: =C11-IFERROR(VLOOKUP("Deudas",Presupuesto!A:B,2,0),0) -> -230000 | F11: =IF(E11<=0,"✅ OK","⚠️ Excedido") -> ✅ OK
B12: ● Entretenimiento | C12: =SUMIF(Transacciones!E:E,"Entretenimiento",Transacciones!D:D) -> 140000 | D12: =IF(Transacciones!C3>0,C12/Transacciones!C3,0) -> 0.091623037 | E12: =C12-IFERROR(VLOOKUP("Entretenimiento",Presupuesto!A:B,2,0),0) -> 40000 | F12: =IF(E12<=0,"✅ OK","⚠️ Excedido") -> ⚠️ Excedido
B13: ● Salud | C13: =SUMIF(Transacciones!E:E,"Salud",Transacciones!D:D) -> 0 | D13: =IF(Transacciones!C3>0,C13/Transacciones!C3,0) -> 0 | E13: =C13-IFERROR(VLOOKUP("Salud",Presupuesto!A:B,2,0),0) -> -50000 | F13: =IF(E13<=0,"✅ OK","⚠️ Excedido") -> ✅ OK
B14: ● Salidas | C14: =SUMIF(Transacciones!E:E,"Salidas",Transacciones!D:D) -> 100000 | D14: =IF(Transacciones!C3>0,C14/Transacciones!C3,0) -> 0.065445026 | E14: =C14-IFERROR(VLOOKUP("Salidas",Presupuesto!A:B,2,0),0) -> -400000 | F14: =IF(E14<=0,"✅ OK","⚠️ Excedido") -> ✅ OK
B15: ● Educación | C15: =SUMIF(Transacciones!E:E,"Educación",Transacciones!D:D) -> 438000 | D15: =IF(Transacciones!C3>0,C15/Transacciones!C3,0) -> 0.28664921 | E15: =C15-IFERROR(VLOOKUP("Educación",Presupuesto!A:B,2,0),0) -> 358000 | F15: =IF(E15<=0,"✅ OK","⚠️ Excedido") -> ⚠️ Excedido
B16: ● Otros | C16: =SUMIF(Transacciones!E:E,"Otros",Transacciones!D:D) -> 0 | D16: =IF(Transacciones!C3>0,C16/Transacciones!C3,0) -> 0 | E16: =C16-IFERROR(VLOOKUP("Otros",Presupuesto!A:B,2,0),0) -> -50000 | F16: =IF(E16<=0,"✅ OK","⚠️ Excedido") -> ✅ OK
B17: ● Ahorro | C17: =SUMIF(Transacciones!E:E,"Ahorro",Transacciones!D:D) -> 80000 | D17: =IF(Transacciones!C3>0,C17/Transacciones!C3,0) -> 0.052356021 | E17: =C17-IFERROR(VLOOKUP("Ahorro",Presupuesto!A:B,2,0),0) -> -120000 | F17: =IF(E17<=0,"✅ OK","⚠️ Excedido") -> ✅ OK
B18: TOTAL | C18: =SUM(C10:C17) -> 1528000 | D18: =SUM(D10:D17) -> 1
B20: ℹ️ Todos los valores se actualizan automáticamente al agregar transacciones en la hoja 'Transacciones'

Sheet Transacciones
A1: Ingresos | B1: Total
A2: Ingresos | C2: =SUMIF(B5:B10000,"Ingreso",D5:D10000) -> 2853000
A3: Egresos | C3: =SUMIF(B5:B10000,"Gasto",D5:D10000) -> 1528000
A4: Balance | C4: =C2-C3 -> 1325000
A5: 📋 REGISTRO DE TRANSACCIONES
A6: Fecha | B6: Tipo | C6: Descripción | D6: Monto | E6: Categoría | F6: Método Pago | G6: Notas
A7: 30/04/2025 | B7: Gasto | C7: Ahorro | D7: 80000 | E7: Ahorro | F7: Transferencia
A8: 30/04/2025 | B8: Gasto | C8: DeudaPapa | D8: 70000 | E8: Deudas | F8: Efectivo
A9: 30/04/2025 | B9: Gasto | C9: RegaloTia | D9: 140000 | E9: Entretenimiento | F9: Tarjeta | G9: Cumpleaños
A10: 30/04/2025 | B10: Gasto | C10: PagoInternet | D10: 72000 | E10: Vivienda | F10: Transferencia | G10: Claro Hogar
A11: 20/04/2025 | B11: Gasto | C11: Mercado de la casa | D11: 450000 | E11: Vivienda | F11: Efectivo
A12: 20/04/2025 | B12: Gasto | C12: AlmuerzFamiliar | D12: 100000 | E12: Salidas | F12: Efectivo
A13: 18/04/2025 | B13: Gasto | C13: Maiz y gastos casa | D13: 178000 | E13: Vivienda | F13: Efectivo
A14: 14/04/2025 | B14: Gasto | C14: Icetex | D14: 438000 | E14: Educación | F14: Transferencia | G14: Cuota abril
A15: 01/04/2025 | B15: Ingreso | C15: Salario | D15: 2853000 | E15: Ingreso | F15: Transferencia | G15: Quincena
A68: 💡 Agrega nuevas filas copiando el formato de las anteriores. Los valores se actualizarán automáticamente en el Resumen.

Sheet Presupuesto
A1: 🎯 PRESUPUESTO MENSUAL
A2: Categoría | B2: Presupuesto | C2: Gastado | D2: Diferencia | E2: % Usado
A3: Vivienda | B3: 1200000 | C3: =SUMIF(Transacciones!E:E,A3,Transacciones!D:D) -> 700000 | D3: =B3-C3 -> 500000 | E3: =IF(B3>0,C3/B3,0) -> 0.58333333
A4: Deudas | B4: 300000 | C4: =SUMIF(Transacciones!E:E,A4,Transacciones!D:D) -> 70000 | D4: =B4-C4 -> 230000 | E4: =IF(B4>0,C4/B4,0) -> 0.23333333
A5: Entretenimiento | B5: 100000 | C5: =SUMIF(Transacciones!E:E,A5,Transacciones!D:D) -> 140000 | D5: =B5-C5 -> -40000 | E5: =IF(B5>0,C5/B5,0) -> 1.4
A6: Salud | B6: 50000 | C6: =SUMIF(Transacciones!E:E,A6,Transacciones!D:D) -> 0 | D6: =B6-C6 -> 50000 | E6: =IF(B6>0,C6/B6,0) -> 0
A7: Salidas | B7: 500000 | C7: =SUMIF(Transacciones!E:E,A7,Transacciones!D:D) -> 100000 | D7: =B7-C7 -> 400000 | E7: =IF(B7>0,C7/B7,0) -> 0.2
A8: Educación | B8: 80000 | C8: =SUMIF(Transacciones!E:E,A8,Transacciones!D:D) -> 438000 | D8: =B8-C8 -> -358000 | E8: =IF(B8>0,C8/B8,0) -> 5.475
A9: Otros | B9: 50000 | C9: =SUMIF(Transacciones!E:E,A9,Transacciones!D:D) -> 0 | D9: =B9-C9 -> 50000 | E9: =IF(B9>0,C9/B9,0) -> 0
A10: Ahorro | B10: 200000 | C10: =SUMIF(Transacciones!E:E,A10,Transacciones!D:D) -> 80000 | D10: =B10-C10 -> 120000 | E10: =IF(B10>0,C10/B10,0) -> 0.4
A11: TOTAL | B11: =SUM(B3:B10) -> 2480000 | C11: =SUM(C3:C10) -> 1528000 | D11: =SUM(D3:D10) -> 952000 | E11: =IF(B11>0,C11/B11,0) -> 0.61612903
A13: ℹ️ Los valores en amarillo son editables. Los demás se calculan automáticamente.

Sheet 📈 Análisis
A1: 📈 ANÁLISIS MENSUAL — DATOS PARA GRÁFICOS
A3: GASTOS POR CATEGORÍA
A4: Categoría | B4: Monto
A5: Vivienda | B5: =SUMIF(Transacciones!E:E,A5,Transacciones!D:D) -> 700000
A6: Deudas | B6: =SUMIF(Transacciones!E:E,A6,Transacciones!D:D) -> 70000
A7: Entretenimiento | B7: =SUMIF(Transacciones!E:E,A7,Transacciones!D:D) -> 140000
A8: Salud | B8: =SUMIF(Transacciones!E:E,A8,Transacciones!D:D) -> 0
A9: Salidas | B9: =SUMIF(Transacciones!E:E,A9,Transacciones!D:D) -> 100000
A10: Educación | B10: =SUMIF(Transacciones!E:E,A10,Transacciones!D:D) -> 438000
A11: Otros | B11: =SUMIF(Transacciones!E:E,A11,Transacciones!D:D) -> 0
A12: Ahorro | B12: =SUMIF(Transacciones!E:E,A12,Transacciones!D:D) -> 80000
A16: INGRESOS VS EGRESOS
A17: Concepto | B17: Monto
A18: Ingresos | B18: =Transacciones!C2 -> 2853000
A19: Egresos | B19: =Transacciones!C3 -> 1528000
A20: Balance | B20: =Transacciones!C4 -> 1325000

Sheet ℹ️ Instrucciones
B1: 📖 GUÍA DE USO — REPORTE FINANCIERO MENSUAL
B4: 🗂️ ESTRUCTURA DEL ARCHIVO
B5: 📊 Resumen | C5: Vista general con KPIs, tabla de categorías y estado vs presupuesto.
B6: 📋 Transacciones | C6: Aquí se registran todos los movimientos. Agrega filas con Fecha, Tipo, Monto, Categoría, etc.
B7: 🎯 Presupuesto | C7: Define cuánto quieres gastar por categoría. Celdas en amarillo son editables.
B8: 📈 Análisis | C8: Gráficos de torta e histograma generados automáticamente con tus datos.
B9: ℹ️ Instrucciones | C9: Esta hoja :)
B11: 🚀 CÓMO USAR
B12: Paso 1 | C12: En la hoja 'Transacciones', agrega cada gasto o ingreso en una nueva fila.
B13: Paso 2 | C13: Asegúrate de usar exactamente los mismos nombres de categoría (Vivienda, Deudas, Salidas, etc.).
B14: Paso 3 | C14: En 'Presupuesto', actualiza los valores en amarillo con tu presupuesto real.
B15: Paso 4 | C15: El 'Resumen' y 'Análisis' se actualizan automáticamente.
B17: 📌 CATEGORÍAS DISPONIBLES | C17: Vivienda | Deudas | Entretenimiento | Salud | Salidas | Educación | Otros | Ahorro
B19: 💡 CONSEJO | C19: Puedes agregar nuevas categorías duplicando una fila en Transacciones y usando un nombre nuevo.
C20: Luego agrega ese nombre en la hoja Presupuesto y actualiza las fórmulas del Resumen.
